reva/__init__.py
reva/advisor_profile.py
reva/autotest.py
reva/autotest_runner.py
reva/branch.py
reva/cli.py
reva/document_access_control.py
reva/exception.py
reva/info.py
reva/loan_products.py
reva/namespaces.py
reva/permissions.py
reva/roles.py
reva/roles_and_permissions.py
reva/site_settings.py
reva/workflow.py
reva/conf/__init__.py
reva/conf/reva.py
reva/lib/__init__.py
reva/lib/advisor_profile/__init__.py
reva/lib/advisor_profile/create.py
reva/lib/advisor_profile/main.py
reva/lib/auto/__init__.py
reva/lib/auto/main.py
reva/lib/autotest_runner/__init__.py
reva/lib/autotest_runner/main.py
reva/lib/base/__init__.py
reva/lib/base/base.py
reva/lib/base/constants.py
reva/lib/base/resource_delete.py
reva/lib/base/resource_update.py
reva/lib/base/run_query.py
reva/lib/base/site_settings.py
reva/lib/base/errors/__init__.py
reva/lib/base/errors/errors.py
reva/lib/branch/__init__.py
reva/lib/branch/create.py
reva/lib/branch/main.py
reva/lib/client/__init__.py
reva/lib/client/aws.py
reva/lib/client/builder.py
reva/lib/client/graphql_client.py
reva/lib/client/lendsmart_client.py
reva/lib/document_access_control/__init__.py
reva/lib/document_access_control/main.py
reva/lib/document_access_control/update.py
reva/lib/graphql_queries/__init__.py
reva/lib/graphql_queries/advisor_profiles.py
reva/lib/graphql_queries/branch.py
reva/lib/graphql_queries/document_access_control.py
reva/lib/graphql_queries/loan_products.py
reva/lib/graphql_queries/namespace.py
reva/lib/graphql_queries/roles_and_permissions.py
reva/lib/graphql_queries/site_settings.py
reva/lib/graphql_queries/workflow.py
reva/lib/loan_productus/__init__.py
reva/lib/loan_productus/main.py
reva/lib/loan_productus/update.py
reva/lib/permissions/__init__.py
reva/lib/permissions/delete.py
reva/lib/permissions/main.py
reva/lib/permissions/update.py
reva/lib/roles/__init__.py
reva/lib/roles/delete.py
reva/lib/roles/main.py
reva/lib/roles/update.py
reva/lib/roles_and_permissions/__init__.py
lendsmart_reva-2.15.dist-info/LICENSE
lendsmart_reva-2.15.dist-info/METADATA
lendsmart_reva-2.15.dist-info/WHEEL
lendsmart_reva-2.15.dist-info/entry_points.txt
lendsmart_reva-2.15.dist-info/top_level.txt
lendsmart_reva-2.15.dist-info/RECORD
