Metadata-Version: 2.1
Name: lendsmart-reva
Version: 2.15
Summary: Lendsmart opinionated tool to mirror QA to Prod. Deploy with ease.
Home-page: https://github.com/lendsmartlabs
Author: Lendsmart
Author-email: accounts@lendsmart.ai
License: MIT
Keywords: lendsmart reva
Classifier: Programming Language :: Python :: 3.8
License-File: LICENSE
Requires-Dist: PyJWT (==2.7.0)
Requires-Dist: cryptography (==37.0.4)
Requires-Dist: lendsmart-api
Requires-Dist: lendsmart-autotest
Requires-Dist: python-graphql-client
Requires-Dist: ramda
Requires-Dist: remoto (>=1.1.4)
Requires-Dist: configparser ; python_version < "3.0"
Requires-Dist: setuptools (<45.0.0) ; python_version < "3.0"
Requires-Dist: setuptools ; python_version >= "3.0"
